fds/__init__.py
fds/sdk/__init__.py
fds/sdk/PriceAlertingAPIforDigitalPortals/__init__.py
fds/sdk/PriceAlertingAPIforDigitalPortals/api_client.py
fds/sdk/PriceAlertingAPIforDigitalPortals/configuration.py
fds/sdk/PriceAlertingAPIforDigitalPortals/exceptions.py
fds/sdk/PriceAlertingAPIforDigitalPortals/model_utils.py
fds/sdk/PriceAlertingAPIforDigitalPortals/rest.py
fds/sdk/PriceAlertingAPIforDigitalPortals/api/__init__.py
fds/sdk/PriceAlertingAPIforDigitalPortals/api/alerting_api.py
fds/sdk/PriceAlertingAPIforDigitalPortals/apis/__init__.py
fds/sdk/PriceAlertingAPIforDigitalPortals/model/__init__.py
fds/sdk/PriceAlertingAPIforDigitalPortals/model/alerting_prices_basic_trigger_list_data.py
fds/sdk/PriceAlertingAPIforDigitalPortals/model/alerting_prices_basic_trigger_list_data_filter.py
fds/sdk/PriceAlertingAPIforDigitalPortals/model/alerting_prices_basic_trigger_list_data_filter_status.py
fds/sdk/PriceAlertingAPIforDigitalPortals/model/alerting_prices_basic_trigger_list_meta.py
fds/sdk/PriceAlertingAPIforDigitalPortals/model/alerting_prices_basic_trigger_list_meta_pagination.py
fds/sdk/PriceAlertingAPIforDigitalPortals/model/attributes_member.py
fds/sdk/PriceAlertingAPIforDigitalPortals/model/cursor_based_pagination_output_object.py
fds/sdk/PriceAlertingAPIforDigitalPortals/model/cursor_based_pagination_output_object_without_total.py
fds/sdk/PriceAlertingAPIforDigitalPortals/model/error_meta_object.py
fds/sdk/PriceAlertingAPIforDigitalPortals/model/error_object.py
fds/sdk/PriceAlertingAPIforDigitalPortals/model/inline_object.py
fds/sdk/PriceAlertingAPIforDigitalPortals/model/inline_response200.py
fds/sdk/PriceAlertingAPIforDigitalPortals/model/inline_response2001.py
fds/sdk/PriceAlertingAPIforDigitalPortals/model/inline_response2001_data.py
fds/sdk/PriceAlertingAPIforDigitalPortals/model/inline_response2001_meta.py
fds/sdk/PriceAlertingAPIforDigitalPortals/model/inline_response2001_trigger.py
fds.sdk.PriceAlertingAPIforDigitalPortals-0.10.3.dist-info/LICENSE
fds.sdk.PriceAlertingAPIforDigitalPortals-0.10.3.dist-info/METADATA
fds.sdk.PriceAlertingAPIforDigitalPortals-0.10.3.dist-info/WHEEL
fds.sdk.PriceAlertingAPIforDigitalPortals-0.10.3.dist-info/top_level.txt
fds.sdk.PriceAlertingAPIforDigitalPortals-0.10.3.dist-info/RECORD
